df_io/__init__.py
tests/__init__.py
tests/test_df_io.py
df_io-0.0.12.dist-info/LICENSE
df_io-0.0.12.dist-info/METADATA
df_io-0.0.12.dist-info/WHEEL
df_io-0.0.12.dist-info/top_level.txt
df_io-0.0.12.dist-info/RECORD
