Metadata-Version: 2.1
Name: df-io
Version: 0.0.12
Summary: Helpers for doing IO with Pandas DataFrames
Home-page: https://github.com/Mikata-Project/df_io
Author: NAGY, Attila
Author-email: nagy.attila@gmail.com
License: UNKNOWN
Platform: UNKNOWN
Classifier: Programming Language :: Python
Classifier: License :: OSI Approved :: MIT License
Classifier: Operating System :: OS Independent
License-File: LICENSE
Requires-Dist: numpy
Requires-Dist: smart-open
Requires-Dist: zstandard
Requires-Dist: pandas
Requires-Dist: parallel-write
Provides-Extra: test
Requires-Dist: boto3 ; extra == 'test'
Requires-Dist: pytest ; extra == 'test'
Requires-Dist: pyarrow ; extra == 'test'
Requires-Dist: lxml ; extra == 'test'
